LICENSE.md
MANIFEST.in
README.rst
setup.py
clibs/warble/LICENSE.md
clibs/warble/Makefile
clibs/warble/README.md
clibs/warble/config.mk
clibs/warble/version.mk
clibs/warble/bin/generate_version.bat
clibs/warble/bin/generate_version.sh
clibs/warble/deps/libblepp/ATT.txt
clibs/warble/deps/libblepp/CMakeLists.txt
clibs/warble/deps/libblepp/COPYING
clibs/warble/deps/libblepp/Makefile.in
clibs/warble/deps/libblepp/Notes.txt
clibs/warble/deps/libblepp/README
clibs/warble/deps/libblepp/att_gatt.h
clibs/warble/deps/libblepp/configure
clibs/warble/deps/libblepp/configure.ac
clibs/warble/deps/libblepp/cxxgplot.h
clibs/warble/deps/libblepp/get_attrs.sh
clibs/warble/deps/libblepp/hex2ascii.awk
clibs/warble/deps/libblepp/libblepp.pc.in
clibs/warble/deps/libblepp/blepp/att.h
clibs/warble/deps/libblepp/blepp/att_pdu.h
clibs/warble/deps/libblepp/blepp/bledevice.h
clibs/warble/deps/libblepp/blepp/blestatemachine.h
clibs/warble/deps/libblepp/blepp/float.h
clibs/warble/deps/libblepp/blepp/gap.h
clibs/warble/deps/libblepp/blepp/lescan.h
clibs/warble/deps/libblepp/blepp/logging.h
clibs/warble/deps/libblepp/blepp/pretty_printers.h
clibs/warble/deps/libblepp/blepp/uuid.h
clibs/warble/deps/libblepp/blepp/xtoa.h
clibs/warble/deps/libblepp/cmake/modules/FindBluez.cmake
clibs/warble/deps/libblepp/examples/blelogger
clibs/warble/deps/libblepp/examples/blelogger.cc
clibs/warble/deps/libblepp/examples/bluetooth
clibs/warble/deps/libblepp/examples/bluetooth.cc
clibs/warble/deps/libblepp/examples/lescan
clibs/warble/deps/libblepp/examples/lescan.cc
clibs/warble/deps/libblepp/examples/lescan_simple
clibs/warble/deps/libblepp/examples/lescan_simple.cc
clibs/warble/deps/libblepp/examples/primary_service_names.cc
clibs/warble/deps/libblepp/examples/read_device_name
clibs/warble/deps/libblepp/examples/read_device_name.cc
clibs/warble/deps/libblepp/examples/temperature
clibs/warble/deps/libblepp/examples/temperature.cc
clibs/warble/deps/libblepp/examples/write
clibs/warble/vs2017/example-read-dev-info/example-read-dev-info.vcxproj
clibs/warble/vs2017/example-read-dev-info/example-read-dev-info.vcxproj.filters
warble.egg-info/PKG-INFO
warble.egg-info/SOURCES.txt
warble.egg-info/dependency_links.txt
warble.egg-info/top_level.txt