Metadata-Version: 1.2
Name: warble
Version: 1.2.8
Summary: Python bindings for MbientLab's Warble library
Home-page: https://github.com/mbientlab/PyWarble
Author: MbientLab
Author-email: hello@mbientlab.com
License: UNKNOWN
Keywords: mbientlab,bluetooth le,native
Platform: UNKNOWN
Classifier: Development Status :: 5 - Production/Stable
Classifier: Intended Audience :: Developers
Classifier: Operating System :: POSIX :: Linux
Classifier: Operating System :: Microsoft :: Windows :: Windows 10
Classifier: Programming Language :: Python :: 3
Requires-Python: >=3.4
